[
  { "id": "81135000", "name": "BALSA DO CERRO" },
  { "id": "81360000", "name": "BARRA DO BATATAL" },
  { "id": "81881000", "name": "BARRAGEM DO VALO GRANDE - JUSANTE" },
  { "id": "81880000", "name": "BARRAGEM DO VALO GRANDE - MONTANTE" },
  { "id": "81200000", "name": "CAPELA DA RIBEIRA" },
  { "id": "81380000", "name": "ELDORADO" },
  { "id": "81107000", "name": "SÃO SEBASTIÃO" },
  { "id": "81350000", "name": "IPORANGA" },
  { "id": "81683000", "name": "REGISTRO" },
  { "id": "81420000", "name": "SETE BARRAS" }
]
